aiogram3_form/__init__.py
aiogram3_form/field.py
aiogram3_form/filters.py
aiogram3_form/form.py
aiogram3_form/utils.py
aiogram3_form-2.0.5.dist-info/LICENSE
aiogram3_form-2.0.5.dist-info/METADATA
aiogram3_form-2.0.5.dist-info/WHEEL
aiogram3_form-2.0.5.dist-info/RECORD
