Metadata-Version: 2.3
Name: aiogram3-form
Version: 2.0.5
Summary: A library for creating forms in aiogram3
License: MIT
Author: TrixiS
Author-email: oficialmorozov@gmail.com
Requires-Python: >=3.10,<4.0
Classifier: License :: OSI Approved :: MIT License
Classifier: Programming Language :: Python :: 3
Classifier: Programming Language :: Python :: 3.10
Classifier: Programming Language :: Python :: 3.11
Classifier: Programming Language :: Python :: 3.12
Classifier: Programming Language :: Python :: 3.13
